dstrace/__init__.py
dstrace/dstrace.py
dstrace/test_utils.py
dstrace/version.py
dstrace/vendor/__init__.py
dstrace/vendor/nbconflux/__init__.py
dstrace/vendor/nbconflux/run_tests.py
dstrace/vendor/nbconflux/setup.py
dstrace/vendor/nbconflux/versioneer.py
dstrace/vendor/nbconflux/nbconflux/__init__.py
dstrace/vendor/nbconflux/nbconflux/__main__.py
dstrace/vendor/nbconflux/nbconflux/_version.py
dstrace/vendor/nbconflux/nbconflux/api.py
dstrace/vendor/nbconflux/nbconflux/cli.py
dstrace/vendor/nbconflux/nbconflux/confluence.tpl
dstrace/vendor/nbconflux/nbconflux/exporter.py
dstrace/vendor/nbconflux/nbconflux/filter.py
dstrace/vendor/nbconflux/nbconflux/markdown.py
dstrace/vendor/nbconflux/nbconflux/preprocessor.py
dstrace-0.1.13.dist-info/LICENSE
dstrace-0.1.13.dist-info/METADATA
dstrace-0.1.13.dist-info/WHEEL
dstrace-0.1.13.dist-info/entry_points.txt
dstrace-0.1.13.dist-info/top_level.txt
dstrace-0.1.13.dist-info/RECORD
