Metadata-Version: 2.1
Name: dstrace
Version: 0.1.13
Summary: Data science workflow automation tool.
Home-page: https://github.com/sancau/dstrace/
Author: Alexander Tatchin
Author-email: alexander.tatchin@gmail.com
License: MIT
Platform: any
Classifier: Development Status :: 3 - Alpha
Classifier: Intended Audience :: Developers
Classifier: Intended Audience :: Information Technology
Classifier: Intended Audience :: Science/Research
Classifier: License :: OSI Approved :: MIT License
Classifier: Operating System :: POSIX
Classifier: Operating System :: MacOS
Classifier: Operating System :: Unix
Classifier: Programming Language :: Python :: 3
Classifier: Topic :: Software Development :: Libraries :: Python Modules
Classifier: Topic :: Scientific/Engineering
License-File: LICENSE
Requires-Dist: fire (<1,>=0.2.1)
Requires-Dist: GitPython (<4,>=3.0.8)
Requires-Dist: html5lib (<2,>=1.0.1)
Requires-Dist: nbconvert (<6,>=5.6.1)
Requires-Dist: PyYAML (<6,>=5.2)
Requires-Dist: requests (<3,>=2.22.0)
Requires-Dist: traitlets (<5,>=4.3.3)
Requires-Dist: bleach (<4,>=3.1.4)
Requires-Dist: Jinja2 (<3.1,>=3.0.0)
